tagth/__init__.py
tagth/tagth.py
tagth-1.2.2.dist-info/licenses/LICENSE
tagth-1.2.2.dist-info/METADATA
tagth-1.2.2.dist-info/WHEEL
tagth-1.2.2.dist-info/top_level.txt
tagth-1.2.2.dist-info/RECORD
