Metadata-Version: 2.4
Name: tagth
Version: 1.2.2
Summary: Pure Python Stateless Tag-Based Authorization Library
Author-email: Boris Resnick <boris.resnick@gmail.com>
Project-URL: Homepage, https://github.com/scartill/tagth
Project-URL: Changelog, https://github.com/scartill/tagth/blob/main/CHANGELOG.md
Requires-Python: >=3.8
License-File: LICENSE
Requires-Dist: pyparsing>=3.1.4
Dynamic: license-file
